{
    "sourceFile": "package.json",
    "activeCommit": 0,
    "commits": [
        {
            "activePatchIndex": 7,
            "patches": [
                {
                    "date": 1638730348607,
                    "content": "Index: \n===================================================================\n--- \n+++ \n"
                },
                {
                    "date": 1638731990525,
                    "content": "Index: \n===================================================================\n--- \n+++ \n@@ -6,9 +6,9 @@\n     \"android\": \"react-native run-android\",\n     \"ios\": \"react-native run-ios --port 8082 --simulator='iPhone 12 Pro Max'\",\n     \"pods\": \"npx pod-install ios\",\n     \"clean\": \"watchman watch-del-all\",\n-    \"start\": \"react-native start --reset-cache\",\n+    \"start\": \"react-native start --port 8082 --reset-cache\",\n     \"test\": \"jest\",\n     \"lint\": \"eslint .\"\n   },\n   \"dependencies\": {\n"
                },
                {
                    "date": 1638732659465,
                    "content": "Index: \n===================================================================\n--- \n+++ \n@@ -3,12 +3,12 @@\n   \"version\": \"0.0.1\",\n   \"private\": true,\n   \"scripts\": {\n     \"android\": \"react-native run-android\",\n-    \"ios\": \"react-native run-ios --port 8082 --simulator='iPhone 12 Pro Max'\",\n+    \"ios\": \"react-native run-ios --simulator='iPhone 12 Pro Max'\",\n     \"pods\": \"npx pod-install ios\",\n     \"clean\": \"watchman watch-del-all\",\n-    \"start\": \"react-native start --port 8082 --reset-cache\",\n+    \"start\": \"react-native start --reset-cache\",\n     \"test\": \"jest\",\n     \"lint\": \"eslint .\"\n   },\n   \"dependencies\": {\n"
                },
                {
                    "date": 1638732944671,
                    "content": "Index: \n===================================================================\n--- \n+++ \n@@ -3,12 +3,12 @@\n   \"version\": \"0.0.1\",\n   \"private\": true,\n   \"scripts\": {\n     \"android\": \"react-native run-android\",\n-    \"ios\": \"react-native run-ios --simulator='iPhone 12 Pro Max'\",\n+    \"ios\": \"react-native run-ios --port 8082 --simulator='iPhone 12 Pro Max'\",\n     \"pods\": \"npx pod-install ios\",\n     \"clean\": \"watchman watch-del-all\",\n-    \"start\": \"react-native start --reset-cache\",\n+    \"start\": \"react-native start --port 8082 --reset-cache\",\n     \"test\": \"jest\",\n     \"lint\": \"eslint .\"\n   },\n   \"dependencies\": {\n"
                },
                {
                    "date": 1638791097487,
                    "content": "Index: \n===================================================================\n--- \n+++ \n@@ -7,8 +7,9 @@\n     \"ios\": \"react-native run-ios --port 8082 --simulator='iPhone 12 Pro Max'\",\n     \"pods\": \"npx pod-install ios\",\n     \"clean\": \"watchman watch-del-all\",\n     \"start\": \"react-native start --port 8082 --reset-cache\",\n+    \"build-all\": \"react-native bundle --platform android --dev false --entry-file index.js --bundle-output android/app/src/main/assets/index.android.bundle --assets-dest android/app/src/main/res && react-native bundle --dev false --entry-file index.js --bundle-output ios/main.jsbundle --platform ios\",\n     \"test\": \"jest\",\n     \"lint\": \"eslint .\"\n   },\n   \"dependencies\": {\n"
                },
                {
                    "date": 1638798431824,
                    "content": "Index: \n===================================================================\n--- \n+++ \n@@ -0,0 +1,58 @@\n+{\n+  \"name\": \"clarondocdoctor\",\n+  \"version\": \"0.0.1\",\n+  \"private\": true,\n+  \"scripts\": {\n+    \"android\": \"react-native run-android\",\n+    \"ios\": \"react-native run-ios --port 8082 --simulator='iPhone 12 Pro Max'\",\n+    \"pods\": \"npx pod-install ios\",\n+    \"clean\": \"watchman watch-del-all\",\n+    \"start\": \"react-native start --port 8082 --reset-cache\",\n+    \"build-all\": \"react-native bundle --platform android --dev false --entry-file index.js --bundle-output android/app/src/main/assets/index.android.bundle --assets-dest android/app/src/main/res && react-native bundle --dev false --entry-file index.js --bundle-output ios/main.jsbundle --platform ios\",\n+    \"test\": \"jest\",\n+    \"lint\": \"eslint .\"\n+  },\n+  \"dependencies\": {\n+    \"@eva-design/eva\": \"^2.1.1\",\n+    \"@react-native-async-storage/async-storage\": \"^1.15.7\",\n+    \"@react-native-firebase/app\": \"^12.8.0\",\n+    \"@react-native-firebase/firestore\": \"^12.8.0\",\n+    \"@react-native-firebase/messaging\": \"^12.8.0\",\n+    \"@react-navigation/bottom-tabs\": \"^6.0.5\",\n+    \"@react-navigation/native\": \"^6.0.2\",\n+    \"@react-navigation/native-stack\": \"^6.1.0\",\n+    \"@react-navigation/stack\": \"^6.0.7\",\n+    \"@ui-kitten/components\": \"^5.1.1\",\n+    \"@ui-kitten/eva-icons\": \"^5.1.1\",\n+    \"axios\": \"^0.21.1\",\n+    \"date-fns\": \"^2.24.0\",\n+    \"react\": \"17.0.2\",\n+    \"react-native\": \"0.65.1\",\n+    \"react-native-agora\": \"^3.4.6\",\n+    \"react-native-callkeep\": \"^4.2.0\",\n+    \"react-native-chart-kit\": \"^6.11.0\",\n+    \"react-native-document-picker\": \"^6.0.4\",\n+    \"react-native-gesture-handler\": \"^1.10.3\",\n+    \"react-native-safe-area-context\": \"^3.3.0\",\n+    \"react-native-screens\": \"^3.6.0\",\n+    \"react-native-svg\": \"^12.1.1\",\n+    \"react-native-uuid\": \"^2.0.1\",\n+    \"react-native-voip-push-notification\": \"^3.3.0\",\n+    \"react-native-web\": \"^0.17.1\",\n+    \"react-native-webview\": \"^11.13.0\"\n+  },\n+  \"devDependencies\": {\n+    \"@babel/core\": \"^7.12.9\",\n+    \"@babel/runtime\": \"^7.12.5\",\n+    \"@react-native-community/eslint-config\": \"^2.0.0\",\n+    \"babel-jest\": \"^26.6.3\",\n+    \"eslint\": \"7.14.0\",\n+    \"jest\": \"^26.6.3\",\n+    \"metro-react-native-babel-preset\": \"^0.66.0\",\n+    \"react-native-codegen\": \"^0.0.7\",\n+    \"react-test-renderer\": \"17.0.2\"\n+  },\n+  \"jest\": {\n+    \"preset\": \"react-native\"\n+  }\n+}\n"
                },
                {
                    "date": 1638798616584,
                    "content": "Index: \n===================================================================\n--- \n+++ \n@@ -3,12 +3,12 @@\n   \"version\": \"0.0.1\",\n   \"private\": true,\n   \"scripts\": {\n     \"android\": \"react-native run-android\",\n-    \"ios\": \"react-native run-ios --port 8082 --simulator='iPhone 12 Pro Max'\",\n+    \"ios\": \"react-native run-ios --port 8083 --simulator='iPhone 12 Pro Max'\",\n     \"pods\": \"npx pod-install ios\",\n     \"clean\": \"watchman watch-del-all\",\n-    \"start\": \"react-native start --port 8082 --reset-cache\",\n+    \"start\": \"react-native start --port 8083 --reset-cache\",\n     \"build-all\": \"react-native bundle --platform android --dev false --entry-file index.js --bundle-output android/app/src/main/assets/index.android.bundle --assets-dest android/app/src/main/res && react-native bundle --dev false --entry-file index.js --bundle-output ios/main.jsbundle --platform ios\",\n     \"test\": \"jest\",\n     \"lint\": \"eslint .\"\n   },\n"
                },
                {
                    "date": 1638990528763,
                    "content": "Index: \n===================================================================\n--- \n+++ \n@@ -3,19 +3,20 @@\n   \"version\": \"0.0.1\",\n   \"private\": true,\n   \"scripts\": {\n     \"android\": \"react-native run-android\",\n-    \"ios\": \"react-native run-ios --port 8083 --simulator='iPhone 12 Pro Max'\",\n+    \"ios\": \"react-native run-ios --simulator='iPhone 12'\",\n     \"pods\": \"npx pod-install ios\",\n     \"clean\": \"watchman watch-del-all\",\n-    \"start\": \"react-native start --port 8083 --reset-cache\",\n+    \"start\": \"react-native start --reset-cache\",\n     \"build-all\": \"react-native bundle --platform android --dev false --entry-file index.js --bundle-output android/app/src/main/assets/index.android.bundle --assets-dest android/app/src/main/res && react-native bundle --dev false --entry-file index.js --bundle-output ios/main.jsbundle --platform ios\",\n     \"test\": \"jest\",\n     \"lint\": \"eslint .\"\n   },\n   \"dependencies\": {\n     \"@eva-design/eva\": \"^2.1.1\",\n     \"@react-native-async-storage/async-storage\": \"^1.15.7\",\n+    \"@react-native-clipboard/clipboard\": \"^1.9.0\",\n     \"@react-native-firebase/app\": \"^12.8.0\",\n     \"@react-native-firebase/firestore\": \"^12.8.0\",\n     \"@react-native-firebase/messaging\": \"^12.8.0\",\n     \"@react-navigation/bottom-tabs\": \"^6.0.5\",\n@@ -25,19 +26,24 @@\n     \"@ui-kitten/components\": \"^5.1.1\",\n     \"@ui-kitten/eva-icons\": \"^5.1.1\",\n     \"axios\": \"^0.21.1\",\n     \"date-fns\": \"^2.24.0\",\n+    \"firebase\": \"8.2.3\",\n+    \"global\": \"^4.4.0\",\n+    \"ios-deploy\": \"^1.11.4\",\n     \"react\": \"17.0.2\",\n     \"react-native\": \"0.65.1\",\n     \"react-native-agora\": \"^3.4.6\",\n     \"react-native-callkeep\": \"^4.2.0\",\n     \"react-native-chart-kit\": \"^6.11.0\",\n     \"react-native-document-picker\": \"^6.0.4\",\n+    \"react-native-elements\": \"^3.4.2\",\n     \"react-native-gesture-handler\": \"^1.10.3\",\n     \"react-native-safe-area-context\": \"^3.3.0\",\n     \"react-native-screens\": \"^3.6.0\",\n     \"react-native-svg\": \"^12.1.1\",\n     \"react-native-uuid\": \"^2.0.1\",\n+    \"react-native-vector-icons\": \"^9.0.0\",\n     \"react-native-voip-push-notification\": \"^3.3.0\",\n     \"react-native-web\": \"^0.17.1\",\n     \"react-native-webview\": \"^11.13.0\"\n   },\n@@ -55,62 +61,4 @@\n   \"jest\": {\n     \"preset\": \"react-native\"\n   }\n }\n-{\n-  \"name\": \"clarondocdoctor\",\n-  \"version\": \"0.0.1\",\n-  \"private\": true,\n-  \"scripts\": {\n-    \"android\": \"react-native run-android\",\n-    \"ios\": \"react-native run-ios --port 8082 --simulator='iPhone 12 Pro Max'\",\n-    \"pods\": \"npx pod-install ios\",\n-    \"clean\": \"watchman watch-del-all\",\n-    \"start\": \"react-native start --port 8082 --reset-cache\",\n-    \"build-all\": \"react-native bundle --platform android --dev false --entry-file index.js --bundle-output android/app/src/main/assets/index.android.bundle --assets-dest android/app/src/main/res && react-native bundle --dev false --entry-file index.js --bundle-output ios/main.jsbundle --platform ios\",\n-    \"test\": \"jest\",\n-    \"lint\": \"eslint .\"\n-  },\n-  \"dependencies\": {\n-    \"@eva-design/eva\": \"^2.1.1\",\n-    \"@react-native-async-storage/async-storage\": \"^1.15.7\",\n-    \"@react-native-firebase/app\": \"^12.8.0\",\n-    \"@react-native-firebase/firestore\": \"^12.8.0\",\n-    \"@react-native-firebase/messaging\": \"^12.8.0\",\n-    \"@react-navigation/bottom-tabs\": \"^6.0.5\",\n-    \"@react-navigation/native\": \"^6.0.2\",\n-    \"@react-navigation/native-stack\": \"^6.1.0\",\n-    \"@react-navigation/stack\": \"^6.0.7\",\n-    \"@ui-kitten/components\": \"^5.1.1\",\n-    \"@ui-kitten/eva-icons\": \"^5.1.1\",\n-    \"axios\": \"^0.21.1\",\n-    \"date-fns\": \"^2.24.0\",\n-    \"react\": \"17.0.2\",\n-    \"react-native\": \"0.65.1\",\n-    \"react-native-agora\": \"^3.4.6\",\n-    \"react-native-callkeep\": \"^4.2.0\",\n-    \"react-native-chart-kit\": \"^6.11.0\",\n-    \"react-native-document-picker\": \"^6.0.4\",\n-    \"react-native-gesture-handler\": \"^1.10.3\",\n-    \"react-native-safe-area-context\": \"^3.3.0\",\n-    \"react-native-screens\": \"^3.6.0\",\n-    \"react-native-svg\": \"^12.1.1\",\n-    \"react-native-uuid\": \"^2.0.1\",\n-    \"react-native-voip-push-notification\": \"^3.3.0\",\n-    \"react-native-web\": \"^0.17.1\",\n-    \"react-native-webview\": \"^11.13.0\"\n-  },\n-  \"devDependencies\": {\n-    \"@babel/core\": \"^7.12.9\",\n-    \"@babel/runtime\": \"^7.12.5\",\n-    \"@react-native-community/eslint-config\": \"^2.0.0\",\n-    \"babel-jest\": \"^26.6.3\",\n-    \"eslint\": \"7.14.0\",\n-    \"jest\": \"^26.6.3\",\n-    \"metro-react-native-babel-preset\": \"^0.66.0\",\n-    \"react-native-codegen\": \"^0.0.7\",\n-    \"react-test-renderer\": \"17.0.2\"\n-  },\n-  \"jest\": {\n-    \"preset\": \"react-native\"\n-  }\n-}\n"
                }
            ],
            "date": 1638730348607,
            "name": "Commit-0",
            "content": "{\n  \"name\": \"clarondocdoctor\",\n  \"version\": \"0.0.1\",\n  \"private\": true,\n  \"scripts\": {\n    \"android\": \"react-native run-android\",\n    \"ios\": \"react-native run-ios --port 8082 --simulator='iPhone 12 Pro Max'\",\n    \"pods\": \"npx pod-install ios\",\n    \"clean\": \"watchman watch-del-all\",\n    \"start\": \"react-native start --reset-cache\",\n    \"test\": \"jest\",\n    \"lint\": \"eslint .\"\n  },\n  \"dependencies\": {\n    \"@eva-design/eva\": \"^2.1.1\",\n    \"@react-native-async-storage/async-storage\": \"^1.15.7\",\n    \"@react-native-firebase/app\": \"^12.8.0\",\n    \"@react-native-firebase/firestore\": \"^12.8.0\",\n    \"@react-native-firebase/messaging\": \"^12.8.0\",\n    \"@react-navigation/bottom-tabs\": \"^6.0.5\",\n    \"@react-navigation/native\": \"^6.0.2\",\n    \"@react-navigation/native-stack\": \"^6.1.0\",\n    \"@react-navigation/stack\": \"^6.0.7\",\n    \"@ui-kitten/components\": \"^5.1.1\",\n    \"@ui-kitten/eva-icons\": \"^5.1.1\",\n    \"axios\": \"^0.21.1\",\n    \"date-fns\": \"^2.24.0\",\n    \"react\": \"17.0.2\",\n    \"react-native\": \"0.65.1\",\n    \"react-native-agora\": \"^3.4.6\",\n    \"react-native-callkeep\": \"^4.2.0\",\n    \"react-native-chart-kit\": \"^6.11.0\",\n    \"react-native-document-picker\": \"^6.0.4\",\n    \"react-native-gesture-handler\": \"^1.10.3\",\n    \"react-native-safe-area-context\": \"^3.3.0\",\n    \"react-native-screens\": \"^3.6.0\",\n    \"react-native-svg\": \"^12.1.1\",\n    \"react-native-uuid\": \"^2.0.1\",\n    \"react-native-voip-push-notification\": \"^3.3.0\",\n    \"react-native-web\": \"^0.17.1\",\n    \"react-native-webview\": \"^11.13.0\"\n  },\n  \"devDependencies\": {\n    \"@babel/core\": \"^7.12.9\",\n    \"@babel/runtime\": \"^7.12.5\",\n    \"@react-native-community/eslint-config\": \"^2.0.0\",\n    \"babel-jest\": \"^26.6.3\",\n    \"eslint\": \"7.14.0\",\n    \"jest\": \"^26.6.3\",\n    \"metro-react-native-babel-preset\": \"^0.66.0\",\n    \"react-native-codegen\": \"^0.0.7\",\n    \"react-test-renderer\": \"17.0.2\"\n  },\n  \"jest\": {\n    \"preset\": \"react-native\"\n  }\n}\n"
        }
    ]
}